Metadata-Version: 2.1
Name: boilerplatecode
Version: 1.0.1
Summary: Productivity tools to make a developer's life easier
Home-page: https://github.com/DanilZherebtsov/boilerplatecode
Download-URL: https://github.com/DanilZherebtsov/boilerplatecode/archive/refs/tags/1.0.1.tar.gz
Author: Author Name (your name)
Author-email: author@email.com
License: MIT
Keywords: password,generate,password generator,productivity,tools,...
Classifier: Development Status :: 4 - Beta
Classifier: Intended Audience :: Developers
Classifier: Topic :: Software Development :: Build Tools
Classifier: License :: OSI Approved :: MIT License
Classifier: Programming Language :: Python :: 3
Classifier: Programming Language :: Python :: 3.4
Classifier: Programming Language :: Python :: 3.5
Classifier: Programming Language :: Python :: 3.6
Classifier: Programming Language :: Python :: 3.7
Classifier: Programming Language :: Python :: 3.8
Classifier: Programming Language :: Python :: 3.9
Classifier: Programming Language :: Python :: 3.10
License-File: LICENSE.txt
